oneNeuron/__init__.py
oneNeuron/perceptron.py
utils/__init__.py
utils/all_utils.py
utils/model.py
Perceptron_Dhruvraj-0.0.2.dist-info/LICENSE
Perceptron_Dhruvraj-0.0.2.dist-info/METADATA
Perceptron_Dhruvraj-0.0.2.dist-info/WHEEL
Perceptron_Dhruvraj-0.0.2.dist-info/top_level.txt
Perceptron_Dhruvraj-0.0.2.dist-info/RECORD
