Metadata-Version: 2.1
Name: Perceptron-Dhruvraj
Version: 0.0.2
Summary: Implementation of perceptron
Home-page: https://github.com/lathiyadhruvraj/perceptron_pypi
Author: Dhruvraj
Author-email: lathiyadhruvraj44@gmail.com
License: UNKNOWN
Project-URL: Bug Tracker, https://github.com/lathiyadhruvraj/perceptron_pypi/issues
Platform: UNKNOWN
Classifier: Programming Language :: Python :: 3
Classifier: License :: OSI Approved :: MIT License
Classifier: Operating System :: OS Independent
Requires-Python: >=3.7
License-File: LICENSE
Requires-Dist: numpy
Requires-Dist: tqdm
Requires-Dist: matplotlib
Requires-Dist: pandas
Requires-Dist: joblib
